{"status":1,"code":200,"message":"Bid result","response":{"response":{"numFound":42313,"start":0,"numFoundExact":true,"docs":[{"id":"8622383","b_id":[8622383],"b_bid_number":["GEM\/2025\/R\/579743"],"b_category_name":["CLIMBAZOLE PIROCTONE OLAMINE LOTION (100ML),LULICONAZOLE 1% CREAM 10GM,CICLOPIROX 8% TOPICAL SOLUTI"],"b_total_quantity":[2700],"b_status":[1],"b_bid_type":[2],"b_is_bunch":[3],"b_type":[0],"b_bid_to_ra":[1],"b_buyer_status":[0],"b_eval_type":[1],"final_start_date_sort":["2025-11-23T13:00:00Z"],"final_end_date_sort":["2025-11-24T13:00:00Z"],"b_is_custom_item":[1],"b_bid_number_parent":["GEM\/2025\/B\/6699194"],"b_id_parent":[8368906],"is_high_value":[false],"b_ra_to_bid":[1],"ra_b_status":[1],"b_is_inactive":[0],"ra_b_buyer_status":[2],"b_cat_id":["home_univ_univ_univ_univ"],"b.b_created_by":["mahesh.ravunnikutty"],"ba_is_single_packet":[0],"is_rc_bid":[0],"ba_official_details_minName":["Ministry of Defence"],"ba_official_details_deptName":["Department of Military Affairs"]},{"id":"8622408","b_id":[8622408],"b_bid_number":["GEM\/2025\/R\/579745"],"b_category_name":["Recruitment \/ Examination Software"],"b_total_quantity":[1],"b_status":[1],"b_bid_type":[2],"b_is_bunch":[1],"b_type":[0],"b_bid_to_ra":[1],"b_buyer_status":[0],"b_eval_type":[0],"final_start_date_sort":["2025-11-23T13:00:00Z"],"final_end_date_sort":["2025-11-24T13:00:00Z"],"bd_category_name":["Recruitment \/ Examination Software"],"b_is_custom_item":[0],"b_bid_number_parent":["GEM\/2025\/B\/6868561"],"b_id_parent":[8562811],"is_high_value":[false],"b_ra_to_bid":[1],"ra_b_status":[1],"b_is_inactive":[0],"ra_b_buyer_status":[2],"b_cat_id":["home_info_soft_pers_recr"],"b.b_created_by":["Comdt1atc"],"ba_is_single_packet":[0],"is_rc_bid":[0],"ba_official_details_minName":["Ministry of Defence"],"ba_official_details_deptName":["Department of Military Affairs"]},{"id":"8622413","b_id":[8622413],"b_bid_number":["GEM\/2025\/R\/579746"],"b_category_name":["4130131022 DRILL TWIST HSS M35 P S J S DIA 3MM X FL 36MM X OAL 65MM,4130344005 DRILL TWIST HSS M35 "],"b_total_quantity":[870],"b_status":[1],"b_bid_type":[2],"b_is_bunch":[5],"b_type":[0],"b_bid_to_ra":[1],"b_buyer_status":[0],"b_eval_type":[1],"final_start_date_sort":["2025-11-23T13:00:00Z"],"final_end_date_sort":["2025-11-24T13:00:00Z"],"b_is_custom_item":[0],"b_bid_number_parent":["GEM\/2025\/B\/6765958"],"b_id_parent":[8445511],"is_high_value":[false],"b_ra_to_bid":[1],"ra_b_status":[1],"b_is_inactive":[0],"ra_b_buyer_status":[2],"b_cat_id":["home_boq_boql_boql_boq"],"b.b_created_by":["JWM_TOOLS"],"ba_is_single_packet":[0],"is_rc_bid":[0],"ba_official_details_minName":["Ministry of Defence"],"ba_official_details_deptName":["Department of Defence Production"]},{"id":"8622392","b_id":[8622392],"b_bid_number":["GEM\/2025\/R\/579744"],"b_category_name":["Natural Cheese (Hard Variety), Processed Cheese, Processed Cheese Spread and Soft Cheese as per IS "],"b_total_quantity":[7450],"b_status":[1],"b_bid_type":[2],"b_is_bunch":[3],"b_type":[0],"b_bid_to_ra":[1],"b_buyer_status":[0],"b_eval_type":[0],"final_start_date_sort":["2025-11-23T13:00:00Z"],"final_end_date_sort":["2025-11-24T13:00:00Z"],"bd_category_name":["Natural Cheese (Hard Variety), Processed Cheese, Processed Cheese Spread and Soft Cheese as per IS 2785,Natural Cheese (Hard Variety), Processed Cheese, Processed Cheese Spread and Soft Cheese as per IS 2785,Natural Cheese (Hard Variety), Processed Cheese, Processed Cheese Spread and Soft Cheese as per IS 2785"],"b_is_custom_item":[0],"b_bid_number_parent":["GEM\/2025\/B\/6884765"],"b_id_parent":[8581330],"is_high_value":[false],"b_ra_to_bid":[1],"ra_b_status":[1],"b_is_inactive":[0],"ra_b_buyer_status":[2],"b_cat_id":["home_food_dair_chee_chee"],"b.b_created_by":["procurement@221"],"ba_is_single_packet":[0],"is_rc_bid":[0],"ba_official_details_minName":["Ministry of Defence"],"ba_official_details_deptName":["Department of Military Affairs"]},{"id":"8622372","b_id":[8622372],"b_bid_number":["GEM\/2025\/R\/579742"],"b_category_name":["Event or Seminar or Workshop or Exhibition or Expo Management Service - National; Theme Based Event"],"b_total_quantity":[1],"b_status":[1],"b_bid_type":[2],"b_is_bunch":[1],"b_type":[1],"b_bid_to_ra":[1],"b_buyer_status":[0],"b_eval_type":[0],"final_start_date_sort":["2025-11-23T13:00:00Z"],"final_end_date_sort":["2025-11-24T13:00:00Z"],"bd_category_name":["Event or Seminar or Workshop or Exhibition or Expo Management Service - National; Theme Based Events; Complete Execution of Activity; Buyer premise; Full day"],"b_is_custom_item":[0],"b_bid_number_parent":["GEM\/2025\/B\/6854753"],"b_id_parent":[8547071],"is_high_value":[false],"b_ra_to_bid":[1],"ra_b_status":[1],"b_is_inactive":[0],"ra_b_buyer_status":[2],"b_cat_id":["services_home_ev80610203_even"],"b.b_created_by":["bycon1.npp.nawabganj"],"ba_is_single_packet":[0],"is_rc_bid":[0],"ba_official_details_deptName":["Urban Development Department Uttar Pradesh"]},{"id":"8622370","b_id":[8622370],"b_bid_number":["GEM\/2025\/R\/579741"],"b_category_name":["Hygienic Cubicle"],"b_total_quantity":[1],"b_status":[1],"b_bid_type":[2],"b_is_bunch":[1],"b_type":[0],"b_bid_to_ra":[1],"b_buyer_status":[0],"b_eval_type":[0],"final_start_date_sort":["2025-11-23T13:00:00Z"],"final_end_date_sort":["2025-11-24T13:00:00Z"],"bd_category_name":["Hygienic Cubicle"],"b_is_custom_item":[1],"b_bid_number_parent":["GEM\/2025\/B\/6776674"],"b_id_parent":[8457689],"is_high_value":[false],"b_ra_to_bid":[1],"ra_b_status":[1],"b_is_inactive":[0],"ra_b_buyer_status":[2],"b_cat_id":["home_univ_univ_univ_univ"],"b.b_created_by":["ankitk29"],"ba_is_single_packet":[0],"is_rc_bid":[0],"ba_official_details_minName":["Ministry of Defence"],"ba_official_details_deptName":["Department of Military Affairs"]},{"id":"8622345","b_id":[8622345],"b_bid_number":["GEM\/2025\/R\/579739"],"b_category_name":["WIRELESS MAIN EQUIPMENT_3037-3040,INTERCOM MAIN EQUIPMENT_3037-3040,POINT TO POINT MAIN EQUIPMENT_3"],"b_total_quantity":[40],"b_status":[1],"b_bid_type":[2],"b_is_bunch":[9],"b_type":[0],"b_bid_to_ra":[1],"b_buyer_status":[0],"b_eval_type":[0],"final_start_date_sort":["2025-11-23T13:00:00Z"],"final_end_date_sort":["2025-11-25T12:00:00Z"],"bd_category_name":["WIRELESS MAIN EQUIPMENT_3037-3040,INTERCOM MAIN EQUIPMENT_3037-3040,POINT TO POINT MAIN EQUIPMENT_3037-3040,DOCUMENTATION-HARDCOPY AND SOFTCOPY_3037-3040,ON BOARD SPARES FOR ALL ABOVE SYSTEMS_3037-3040,INSTALLATION MATERIAL ALL ABOVE SYSTEMS_3037-3040,SERVICE OF ENGINEERS_3037-3040,TRAINING_3037-3040,INTERCOME ADDITIONAL ITEM_3037-3040"],"b_is_custom_item":[0],"b_bid_number_parent":["GEM\/2025\/B\/6381107"],"b_id_parent":[8008248],"is_high_value":[false],"b_ra_to_bid":[1],"ra_b_status":[1],"b_is_inactive":[0],"ra_b_buyer_status":[2],"b_cat_id":["home_boq_boql_boql_boq"],"b.b_created_by":["Kumar.Bhupendra"],"ba_is_single_packet":[0],"is_rc_bid":[0],"ba_official_details_minName":["Ministry of Defence"],"ba_official_details_deptName":["Department of Defence Production"],"bd_details_is_boq":[true],"bd_details_new_boq":[true]},{"id":"8622343","b_id":[8622343],"b_bid_number":["GEM\/2025\/R\/579738"],"b_category_name":["Natural Cheese (Hard Variety), Processed Cheese, Processed Cheese Spread and Soft Cheese as per IS "],"b_total_quantity":[600],"b_status":[1],"b_bid_type":[2],"b_is_bunch":[1],"b_type":[0],"b_bid_to_ra":[1],"b_buyer_status":[0],"b_eval_type":[0],"final_start_date_sort":["2025-11-23T13:00:00Z"],"final_end_date_sort":["2025-11-24T13:00:00Z"],"bd_category_name":["Natural Cheese (Hard Variety), Processed Cheese, Processed Cheese Spread and Soft Cheese as per IS 2785"],"b_is_custom_item":[0],"b_bid_number_parent":["GEM\/2025\/B\/6900957"],"b_id_parent":[8599804],"is_high_value":[false],"b_ra_to_bid":[1],"ra_b_status":[1],"b_is_inactive":[0],"ra_b_buyer_status":[2],"b_cat_id":["home_food_dair_chee_chee"],"b.b_created_by":["buyer@68isupplasc"],"ba_is_single_packet":[0],"is_rc_bid":[0],"ba_official_details_minName":["Ministry of Defence"],"ba_official_details_deptName":["Department of Military Affairs"]},{"id":"8622641","b_id":[8622641],"b_bid_number":["GEM\/2025\/R\/579787"],"b_category_name":["U JOINT GREASE (POLARIS)"],"b_total_quantity":[40],"b_status":[1],"b_bid_type":[2],"b_is_bunch":[1],"b_type":[0],"b_bid_to_ra":[1],"b_buyer_status":[0],"b_eval_type":[0],"final_start_date_sort":["2025-11-23T13:00:00Z"],"final_end_date_sort":["2025-11-24T13:00:00Z"],"bd_category_name":["U JOINT GREASE (POLARIS)"],"b_is_custom_item":[1],"b_bid_number_parent":["GEM\/2025\/B\/6857915"],"b_id_parent":[8550626],"is_high_value":[false],"b_ra_to_bid":[1],"ra_b_status":[1],"b_is_inactive":[0],"ra_b_buyer_status":[2],"b_cat_id":["home_univ_univ_univ_univ"],"b.b_created_by":["Sangeet519"],"ba_is_single_packet":[0],"is_rc_bid":[0],"ba_official_details_minName":["Ministry of Defence"],"ba_official_details_deptName":["Department of Military Affairs"]},{"id":"8622637","b_id":[8622637],"b_bid_number":["GEM\/2025\/R\/579786"],"b_category_name":["CO2 GAS REGULATOR,PRE HEATER,GAS FLOW METER"],"b_total_quantity":[60],"b_status":[1],"b_bid_type":[2],"b_is_bunch":[3],"b_type":[0],"b_bid_to_ra":[1],"b_buyer_status":[0],"b_eval_type":[0],"final_start_date_sort":["2025-11-23T13:00:00Z"],"final_end_date_sort":["2025-11-24T13:00:00Z"],"bd_category_name":["CO2 GAS REGULATOR,PRE HEATER,GAS FLOW METER"],"b_is_custom_item":[1],"b_bid_number_parent":["GEM\/2025\/B\/6468463"],"b_id_parent":[8106996],"is_high_value":[false],"b_ra_to_bid":[1],"ra_b_status":[1],"b_is_inactive":[0],"ra_b_buyer_status":[2],"b_cat_id":["home_univ_univ_univ_univ"],"b.b_created_by":["ashokbb@beml"],"ba_is_single_packet":[0],"is_rc_bid":[0],"ba_official_details_minName":["Ministry of Defence"],"ba_official_details_deptName":["Department of Defence Production"]}]}}}