{"status":1,"code":200,"message":"Bid result","response":{"response":{"numFound":40442,"start":0,"numFoundExact":true,"docs":[{"id":"8632987","b_id":[8632987],"b_bid_number":["GEM\/2025\/R\/581230"],"b_category_name":["Modular Toilet"],"b_total_quantity":[2],"b_status":[1],"b_bid_type":[2],"b_is_bunch":[1],"b_type":[0],"b_bid_to_ra":[1],"b_buyer_status":[0],"b_eval_type":[0],"final_start_date_sort":["2025-11-26T15:00:00Z"],"final_end_date_sort":["2025-11-27T16:00:00Z"],"bd_category_name":["Modular Toilet"],"b_is_custom_item":[0],"b_bid_number_parent":["GEM\/2025\/B\/6807292"],"b_id_parent":[8492339],"is_high_value":[false],"b_ra_to_bid":[1],"ra_b_status":[1],"b_is_inactive":[0],"ra_b_buyer_status":[2],"b_cat_id":["home_land_port_port_modu"],"b.b_created_by":["narwana@ulbharyana.gov.in"],"ba_is_single_packet":[0],"is_rc_bid":[0],"ba_official_details_deptName":["Urban Local Bodies"]},{"id":"8632990","b_id":[8632990],"b_bid_number":["GEM\/2025\/R\/581231"],"b_category_name":["Ignition Switch,Pump,D Plate,Spring Brake,Hub Seal"],"b_total_quantity":[226],"b_status":[1],"b_bid_type":[2],"b_is_bunch":[5],"b_type":[0],"b_bid_to_ra":[1],"b_buyer_status":[0],"b_eval_type":[0],"final_start_date_sort":["2025-11-26T15:00:00Z"],"final_end_date_sort":["2025-11-27T15:00:00Z"],"bd_category_name":["Ignition Switch,Pump,D Plate,Spring Brake,Hub Seal"],"b_is_custom_item":[0],"b_bid_number_parent":["GEM\/2025\/B\/6880145"],"b_id_parent":[8576117],"is_high_value":[false],"b_ra_to_bid":[1],"ra_b_status":[1],"b_is_inactive":[0],"ra_b_buyer_status":[2],"b_cat_id":["home_boq_boql_boql_boq"],"b.b_created_by":["tyagir@tusker"],"ba_is_single_packet":[0],"is_rc_bid":[0],"ba_official_details_minName":["Ministry of Defence"],"ba_official_details_deptName":["Department of Military Affairs"],"bd_details_is_boq":[true],"bd_details_new_boq":[true]},{"id":"8632968","b_id":[8632968],"b_bid_number":["GEM\/2025\/R\/581229"],"b_category_name":["Parts Kit,Speedometer,Starter,Handle,Seal"],"b_total_quantity":[184],"b_status":[1],"b_bid_type":[2],"b_is_bunch":[5],"b_type":[0],"b_bid_to_ra":[1],"b_buyer_status":[0],"b_eval_type":[0],"final_start_date_sort":["2025-11-26T15:00:00Z"],"final_end_date_sort":["2025-11-27T15:00:00Z"],"bd_category_name":["Parts Kit,Speedometer,Starter,Handle,Seal"],"b_is_custom_item":[0],"b_bid_number_parent":["GEM\/2025\/B\/6880178"],"b_id_parent":[8576154],"is_high_value":[false],"b_ra_to_bid":[1],"ra_b_status":[1],"b_is_inactive":[0],"ra_b_buyer_status":[2],"b_cat_id":["home_boq_boql_boql_boq"],"b.b_created_by":["tyagir@tusker"],"ba_is_single_packet":[0],"is_rc_bid":[0],"ba_official_details_minName":["Ministry of Defence"],"ba_official_details_deptName":["Department of Military Affairs"],"bd_details_is_boq":[true],"bd_details_new_boq":[true]},{"id":"8632964","b_id":[8632964],"b_bid_number":["GEM\/2025\/R\/581228"],"b_category_name":["Fogging Machine (V2) as per IS 14855 (Part 1)"],"b_total_quantity":[1],"b_status":[1],"b_bid_type":[2],"b_is_bunch":[1],"b_type":[0],"b_bid_to_ra":[1],"b_buyer_status":[0],"b_eval_type":[0],"final_start_date_sort":["2025-11-26T15:00:00Z"],"final_end_date_sort":["2025-11-27T15:00:00Z"],"bd_category_name":["Fogging Machine (V2) as per IS 14855 (Part 1)"],"b_is_custom_item":[0],"b_bid_number_parent":["GEM\/2025\/B\/6628125"],"b_id_parent":[8288124],"is_high_value":[false],"b_ra_to_bid":[1],"ra_b_status":[1],"b_is_inactive":[0],"ra_b_buyer_status":[2],"b_cat_id":["home_fa68031381_agri_disp_fogg"],"b.b_created_by":["CONSKUDRA2"],"ba_is_single_packet":[0],"is_rc_bid":[0],"ba_official_details_deptName":["Urban Development & Housing Department Bihar"]},{"id":"8632963","b_id":[8632963],"b_bid_number":["GEM\/2025\/R\/581227"],"b_category_name":["32 CH NVR with 2 SATA Slot,2MP IP PTZ Camera 30 X,5MP IP Bullet Camera with 50 MTR IR,Outdoor Junct"],"b_total_quantity":[4453],"b_status":[1],"b_bid_type":[2],"b_is_bunch":[26],"b_type":[0],"b_bid_to_ra":[1],"b_buyer_status":[0],"b_eval_type":[0],"final_start_date_sort":["2025-11-26T15:00:00Z"],"final_end_date_sort":["2025-11-27T15:00:00Z"],"bd_category_name":["32 CH NVR with 2 SATA Slot,2MP IP PTZ Camera 30 X,5MP IP Bullet Camera with 50 MTR IR,Outdoor Junction Boxes with inbuilt PDUs for media convertors oblique POE oblique Adaptors etc,04 plus 02 Port POE Switch,Cat 6 cable twisted pair to enhance performance cable for transmission of high speed data comma digital oblique analog voice and video for outdoor use,24 Port Gigabit Switch NON POE Unmanaged switch 10 oblique 100 oblique 1000,16 Port Gigabit Switch NON POE,LED HD TV 55 Inch Master Control Display Unit,LED TV 43 Inch Secondary Display Unit,Optical Patch Cords,Fiber Splicing Jointing Kits,Fiber Terminal Box 12F,12 U Rack Fully Loaded Indoor,HDMI Cable 5 Mtr,Optical Fiber Cable 12F Optical Fiber Cable Armoured,LED TV 32 Inch,4 Channel HD DVR,Power Cable 2 Core 1 Point 5 Sqmm Power Cable,Internal Storage Device 4 TB HDD,Media Convertor Pair Single Mode and Optical Fiber Media Convertor distance greater then and equal to 20 Kms,Artificial Intelligence Box for 16 Camera Human Intrusion Detection,UPS 3 Point 2 "],"b_is_custom_item":[0],"b_bid_number_parent":["GEM\/2025\/B\/6597309"],"b_id_parent":[8252986],"is_high_value":[false],"b_ra_to_bid":[1],"ra_b_status":[1],"b_is_inactive":[0],"ra_b_buyer_status":[2],"b_cat_id":["home_boq_boql_boql_boq"],"b.b_created_by":["Buyer@59weu"],"ba_is_single_packet":[0],"is_rc_bid":[0],"ba_official_details_minName":["Ministry of Defence"],"ba_official_details_deptName":["Department of Military Affairs"],"bd_details_is_boq":[true],"bd_details_new_boq":[true]},{"id":"8632947","b_id":[8632947],"b_bid_number":["GEM\/2025\/R\/581226"],"b_category_name":["CONVEYOR GRAVITY ROLLER STRAIGHT LENGTH 8\""],"b_total_quantity":[1],"b_status":[1],"b_bid_type":[2],"b_is_bunch":[1],"b_type":[0],"b_bid_to_ra":[1],"b_buyer_status":[0],"b_eval_type":[0],"final_start_date_sort":["2025-11-26T15:00:00Z"],"final_end_date_sort":["2025-11-27T15:00:00Z"],"bd_category_name":["CONVEYOR GRAVITY ROLLER STRAIGHT LENGTH 8\""],"b_is_custom_item":[1],"b_bid_number_parent":["GEM\/2025\/B\/6832806"],"b_id_parent":[8521749],"is_high_value":[false],"b_ra_to_bid":[1],"ra_b_status":[1],"b_is_inactive":[0],"ra_b_buyer_status":[2],"b_cat_id":["home_univ_univ_univ_univ"],"b.b_created_by":["shubham_33lpo"],"ba_is_single_packet":[0],"is_rc_bid":[0],"ba_official_details_minName":["Ministry of Defence"],"ba_official_details_deptName":["Department of Military Affairs"]},{"id":"8632943","b_id":[8632943],"b_bid_number":["GEM\/2025\/R\/581225"],"b_category_name":["Kit Slave,Nozzle,Air Dryer,Front Hub,Seal"],"b_total_quantity":[247],"b_status":[1],"b_bid_type":[2],"b_is_bunch":[5],"b_type":[0],"b_bid_to_ra":[1],"b_buyer_status":[0],"b_eval_type":[0],"final_start_date_sort":["2025-11-26T15:00:00Z"],"final_end_date_sort":["2025-11-27T15:00:00Z"],"bd_category_name":["Kit Slave,Nozzle,Air Dryer,Front Hub,Seal"],"b_is_custom_item":[0],"b_bid_number_parent":["GEM\/2025\/B\/6880023"],"b_id_parent":[8575985],"is_high_value":[false],"b_ra_to_bid":[1],"ra_b_status":[1],"b_is_inactive":[0],"ra_b_buyer_status":[2],"b_cat_id":["home_boq_boql_boql_boq"],"b.b_created_by":["tyagir@tusker"],"ba_is_single_packet":[0],"is_rc_bid":[0],"ba_official_details_minName":["Ministry of Defence"],"ba_official_details_deptName":["Department of Military Affairs"],"bd_details_is_boq":[true],"bd_details_new_boq":[true]},{"id":"8632933","b_id":[8632933],"b_bid_number":["GEM\/2025\/R\/581224"],"b_category_name":["All in One PC (V2),High End Laptop - Notebook,Line Interactive UPS with AVR (V2),Multifunction Mach"],"b_total_quantity":[40],"b_status":[1],"b_bid_type":[2],"b_is_bunch":[5],"b_type":[0],"b_bid_to_ra":[1],"b_buyer_status":[0],"b_eval_type":[0],"final_start_date_sort":["2025-11-26T15:00:00Z"],"final_end_date_sort":["2025-11-27T15:00:00Z"],"bd_category_name":["All in One PC (V2),High End Laptop - Notebook,Line Interactive UPS with AVR (V2),Multifunction Machine MFM (V2),Multifunction Machine MFM (V2)"],"b_is_custom_item":[0],"b_bid_number_parent":["GEM\/2025\/B\/6891582"],"b_id_parent":[8589029],"is_high_value":[false],"b_ra_to_bid":[1],"ra_b_status":[1],"b_is_inactive":[0],"ra_b_buyer_status":[2],"b_cat_id":["home_info_comp_comp_al55870105,home_info_comp_comp_hi86310775,home_elec_elec_powe_li30614140,home_offi_offi_dupl_mu68711346"],"b.b_created_by":["buycon11.gmcah.jk@gembuyer.in"],"ba_is_single_packet":[0],"is_rc_bid":[0],"ba_official_details_deptName":["Health and Family Welfare Department Jammu and Kashmir"]},{"id":"8632932","b_id":[8632932],"b_bid_number":["GEM\/2025\/R\/581223"],"b_category_name":["Short Term Cab & Taxi Hiring Services - Premium SUV; Outstation; 300Kms x 10Hrs,Bus Hiring Service "],"b_total_quantity":[24],"b_status":[1],"b_bid_type":[2],"b_is_bunch":[3],"b_type":[1],"b_bid_to_ra":[1],"b_buyer_status":[0],"b_eval_type":[0],"final_start_date_sort":["2025-11-26T15:00:00Z"],"final_end_date_sort":["2025-11-27T15:00:00Z"],"bd_category_name":["Bus Hiring Service - Short Term - Outstation; 22-24; A.C. Deluxe (ACX); 300,Bus Hiring Service - Short Term - Outstation; more than 52; A.C. Deluxe (ACX); 300,Short Term Cab & Taxi Hiring Services - Premium SUV; Outstation; 300Kms x 10Hrs"],"b_is_custom_item":[0],"b_bid_number_parent":["GEM\/2025\/B\/6774799"],"b_id_parent":[8455550],"is_high_value":[false],"b_ra_to_bid":[1],"ra_b_status":[1],"b_is_inactive":[0],"ra_b_buyer_status":[2],"b_cat_id":["services_home_ve54336454_shor,services_home_ve54336454_bush"],"b.b_created_by":["logistics49"],"ba_is_single_packet":[0],"is_rc_bid":[0],"ba_official_details_minName":["Ministry of Defence"],"ba_official_details_deptName":["Department of Military Affairs"]},{"id":"8633168","b_id":[8633168],"b_bid_number":["GEM\/2025\/R\/581250"],"b_category_name":["IWB Fitting (90 degree Elbow) of Drawing No: HWPM\/MU\/284 as per enclosed Annexure-TS,IWB Fitting (4"],"b_total_quantity":[16],"b_status":[1],"b_bid_type":[2],"b_is_bunch":[4],"b_type":[0],"b_bid_to_ra":[1],"b_buyer_status":[0],"b_eval_type":[1],"final_start_date_sort":["2025-11-26T15:00:00Z"],"final_end_date_sort":["2025-11-27T15:00:00Z"],"b_is_custom_item":[1],"b_bid_number_parent":["GEM\/2025\/B\/6628537"],"b_id_parent":[8288601],"is_high_value":[false],"b_ra_to_bid":[1],"ra_b_status":[1],"b_is_inactive":[0],"ra_b_buyer_status":[2],"b_cat_id":["home_univ_univ_univ_univ"],"b.b_created_by":["aporpum"],"ba_is_single_packet":[0],"is_rc_bid":[0],"ba_official_details_minName":["PMO"],"ba_official_details_deptName":["Department of Atomic Energy"]}]}}}